celldino/__init__.py
celldino/pl/__init__.py
celldino/pl/basic.py
celldino/pp/__init__.py
celldino/pp/basic.py
celldino/tl/__init__.py
celldino/tl/basic.py
celldino-0.0.0.dist-info/METADATA
celldino-0.0.0.dist-info/WHEEL
celldino-0.0.0.dist-info/licenses/LICENSE
celldino-0.0.0.dist-info/RECORD
